sdypy/__init__.py
sdypy/core/__init__.py
sdypy/testing/__init__.py
sdypy-0.5.1.dist-info/METADATA
sdypy-0.5.1.dist-info/WHEEL
sdypy-0.5.1.dist-info/licenses/LICENSE
sdypy-0.5.1.dist-info/RECORD
