Metadata-Version: 2.4
Name: sdypy
Version: 0.5.1
Summary: SDyPy - Structural Dynamics Python
Project-URL: homepage, https://github.com/sdypy/sdypy
Project-URL: documentation, https://sdypy.readthedocs.io/en/latest/
Project-URL: source, https://github.com/sdypy/sdypy
Author-email: "Janko Slavič et al." <janko.slavic@fs.uni-lj.si>
Maintainer-email: "Janko Slavič et al." <janko.slavic@fs.uni-lj.si>
License-Expression: MIT
License-File: LICENSE
Keywords: Python,Structural Dynamics
Classifier: Development Status :: 5 - Production/Stable
Classifier: Intended Audience :: Developers
Classifier: License :: OSI Approved :: MIT License
Classifier: Programming Language :: Python :: 3.10
Classifier: Topic :: Scientific/Engineering
Requires-Python: >=3.10
Requires-Dist: sdypy-ema
Requires-Dist: sdypy-excitation
Requires-Dist: sdypy-frf
Requires-Dist: sdypy-io
Requires-Dist: sdypy-model
Requires-Dist: sdypy-sep005
Requires-Dist: sdypy-view
Provides-Extra: dev
Requires-Dist: build; extra == 'dev'
Requires-Dist: pytest; extra == 'dev'
Requires-Dist: sphinx; extra == 'dev'
Requires-Dist: sphinx-copybutton>=0.5.2; extra == 'dev'
Requires-Dist: sphinx-rtd-theme; extra == 'dev'
Requires-Dist: twine; extra == 'dev'
Requires-Dist: wheel; extra == 'dev'
